trend_lines/__init__.py
trend_lines/factories/__init__.py
trend_lines/factories/board.py
trend_lines/generator.py
trend_lines/models/__init__.py
trend_lines/models/board.py
trend_lines/models/line.py
trend_lines/models/side.py
trend_lines/models/time.py
trend_lines/utils.py
trend_lines_generator-1.0.3.dist-info/METADATA
trend_lines_generator-1.0.3.dist-info/WHEEL
trend_lines_generator-1.0.3.dist-info/RECORD
