Metadata-Version: 2.1
Name: trend-lines-generator
Version: 1.0.3
Summary: Trend lines generator.
Home-page: https://github.com/nanvel/trend-lines-generator
License: MIT
Keywords: trendlines,trend lines,trend,ta,resistance,support,technical,indicators,financial
Author: Oleksandr Polieno
Author-email: polyenoom@gmail.com
Requires-Python: >=3.10,<4.0
Classifier: License :: OSI Approved :: MIT License
Classifier: Programming Language :: Python :: 3
Classifier: Programming Language :: Python :: 3.10
Classifier: Programming Language :: Python :: 3.11
Classifier: Programming Language :: Python :: 3.12
Requires-Dist: pandas (>=2.2,<3.0)
Requires-Dist: pyarrow (>=16.1.0,<17.0.0)
Project-URL: Repository, https://github.com/nanvel/trend-lines-generator
